python_testui-1.2.5.dist-info/licenses/LICENSE
tests/__init__.py
tests/appium_app_test.py
tests/appium_ios_app.py
tests/appium_tests.py
tests/selenium_firefox_tests.py
tests/selenium_tests.py
tests/screens/__init__.py
tests/screens/landing.py
testui/__init__.py
testui/elements/__init__.py
testui/elements/testui_collection.py
testui/elements/testui_element.py
testui/support/__init__.py
testui/support/api_support.py
testui/support/appium_driver.py
testui/support/configuration.py
testui/support/helpers.py
testui/support/logger.py
testui/support/parallel.py
testui/support/testui_driver.py
testui/support/testui_images.py
python_testui-1.2.5.dist-info/METADATA
python_testui-1.2.5.dist-info/WHEEL
python_testui-1.2.5.dist-info/top_level.txt
python_testui-1.2.5.dist-info/RECORD
