Metadata-Version: 2.4
Name: python-testui
Version: 1.2.5
Summary: Browser and Mobile automation framework
Home-page: https://github.com/testdevlab/Py-TestUI
Author: Alvaro Santos Laserna Lopez
License: Apache LICENSE 2.0
Project-URL: Source, https://github.com/testdevlab/Py-TestUI
Project-URL: Tracker, https://github.com/testdevlab/Py-TestUI/issues
Project-URL: TestDevLab, https://www.testdevlab.com/
Keywords: Py-TestUI,mobile automation,browser automation
Classifier: Development Status :: 5 - Production/Stable
Classifier: Intended Audience :: Developers
Classifier: Topic :: Software Development :: Quality Assurance
Classifier: License :: OSI Approved :: Apache Software License
Classifier: Programming Language :: Python :: 3
Classifier: Programming Language :: Python :: 3.7
Classifier: Programming Language :: Python :: 3.8
Classifier: Programming Language :: Python :: 3.9
Classifier: Programming Language :: Python :: 3.10
Requires-Python: >=3.6, <4
License-File: LICENSE
Requires-Dist: pytest<=8.0.1
Requires-Dist: Appium-Python-Client~=3.1.1
Requires-Dist: opencv-python~=4.8.1
Requires-Dist: geckodriver-autoinstaller==0.1.0
Requires-Dist: pytest-xdist~=2.5.0
Requires-Dist: pytest-testrail~=2.9.0
Requires-Dist: pure-python-adb==0.3.0.dev0
Requires-Dist: webdriver-manager~=4.0.1
Requires-Dist: numpy~=1.26
Requires-Dist: imutils~=0.5.4
Dynamic: author
Dynamic: classifier
Dynamic: description
Dynamic: description-content-type
Dynamic: home-page
Dynamic: keywords
Dynamic: license
Dynamic: license-file
Dynamic: project-url
Dynamic: requires-dist
Dynamic: requires-python
Dynamic: summary
